twopilabs/utils/usbcdc/__init__.py
twopilabs/utils/usbcdc/usbcdc_base.py
twopilabs/utils/usbcdc/usbcdc_device.py
twopilabs/utils/usbcdc/usbcdc_device_address.py
twopilabs/utils/usbcdc/usbcdc_device_info.py
twopilabs/utils/usbcdc/usbcdc_exception.py
twopilabs_utils_usbcdc-0.1.1.dist-info/LICENSE
twopilabs_utils_usbcdc-0.1.1.dist-info/METADATA
twopilabs_utils_usbcdc-0.1.1.dist-info/WHEEL
twopilabs_utils_usbcdc-0.1.1.dist-info/top_level.txt
twopilabs_utils_usbcdc-0.1.1.dist-info/RECORD
