Metadata-Version: 2.1
Name: twopilabs-utils-usbcdc
Version: 0.1.1
Summary: Native USB CDC ACM implementation using PyUSB
Home-page: https://www.2pi-labs.com
Author: 2pi-Labs GmbH
Author-email: opensource@2pi-labs.com
License: LGPLv3
Platform: UNKNOWN
Classifier: License :: OSI Approved :: GNU Lesser General Public License v3 (LGPLv3)
Classifier: Programming Language :: Python :: 3
Requires-Python: >=3.6
License-File: LICENSE
Requires-Dist: pyusb
Requires-Dist: libusb
